{
  "id": "mem_20250603_223045_029622",
  "content": {
    "interaction": {
      "input": "Complex multi-faceted problem involving artificial intelligence, machine learning, neural networks, cognitive science, and computational neuroscience research",
      "response": "I understand you said: 'Complex multi-faceted problem involving artificial intelligence, machine learning, neural networks, cognitive science, and computational neuroscience research'. This is a placeholder response (I found 5 related memories).",
      "timestamp": "2025-06-03 22:30:45.029622"
    },
    "cognitive_state": {
      "attention_score": 0.8029043555110353,
      "fatigue_level": 0.009928512500000002,
      "relevance": 0.8637299402569619
    }
  },
  "memory_type": "episodic",
  "encoding_time": "2025-06-03T22:30:45.029622",
  "last_access": "2025-06-03T22:30:45.029622",
  "access_count": 0,
  "importance": 0.8637299402569619,
  "emotional_valence": 0.5,
  "confidence": 1.0,
  "source": "unknown",
  "tags": [
    "conversation",
    "interaction"
  ],
  "associations": [],
  "consolidation_count": 0
}